{"Snoop Dogg": {"Emerald": 1.916, "King Ruby": 2.011, "Doberman": 3.4305000000000003, "King Snoop": 5.7005, "Goldizzle": 7.0405, "Black Gold": 1.9730000000000003, "AI Dogg": 3.1265, "Sapphire": 2.2199999999999998, "Black Diamond": 2.1915, "Green Light": 1.8780000000000001, "Chrome": 2.448, "Doggfather": 3.1834999999999996, "Onyx Black": 3.066666666666667, "Black": 9.723076923076922, "just": 1.53}, "Swag Bag": {"Take It Easy": 2.7540000000000004, "P.I.M.P.": 2.1420000000000003, "Gin & Jewels": 2.448, "Leopard": 2.244, "Cashback": 3.1620000000000004, "Boiling Hot": 2.448, "Missionary": 8.969999999999999, "Golden Nugs": 2.3459999999999996, "Bulk Order": 2.244, "Snoop Life": 2.7540000000000004, "Happy Herbs": 3.1620000000000004, "April 20th": 3.1620000000000004, "Darkness": 2.3868, "Onyx Black": 3.485, "Black": 7.5200000000000005, "just": 1.734}, "Snoop Cigar": {"Onyx Black": 8.375, "Black": 17.424999999999997, "just": 4.1225}, "Lol Pop": {"Hexed Helix": 1.8125, "Blood Ember": 1.595, "Pink Foil": 1.5225, "Andromeda": 1.9575, "Celestia": 2.2475, "Fire Vortex": 1.5225, "Gold Star": 1.5225, "Love Bubbles": 1.6674999999999998, "Pumpkin": 1.74, "Jinxed": 1.595, "Heart Pop": 1.595, "Satellite": 1.8125, "Sick Leave": 1.5225, "Mortal Sin": 2.9, "Dark Portal": 1.6965, "Angelina": 2.2475, "Dark Sky": 1.595, "Glowstick": 1.9575, "Doodle Art": 1.6674999999999998, "Cobweb": 1.595, "Crystal Comet": 1.5225, "Einstein": 1.6674999999999998, "Hollywood": 1.5225, "Magic Wand": 1.5225, "Milky Way": 1.5225, "Comic Crunch": 1.5225, "Sweetheart": 1.74, "Watermelon": 1.5225, "Shock Wave": 1.5225, "Blood Sucker": 1.885, "Rosebud": 1.74, "Jolly Roger": 1.6965, "Onyx Black": 1.975, "Black": 5.159999999999999, "just": 1.2325}, "B-Day Candle": {"Happy Meows": 2.1235000000000004, "Purr Magic": 2.1235000000000004, "Final Boss": 2.1235000000000004, "Kaboom!": 2.1235000000000004, "Payday": 2.1235000000000004, "On Fire": 2.1235000000000004, "Pixel Wish": 2.1235000000000004, "Onyx Black": 1.7850000000000001, "Black": 5.085000000000001, "just": 1.1645}, "Desk Calendar": {"Balloon Face": 1.8125, "Investor": 9.475, "Sunday": 1.9575, "Independence": 2.2475, "Pepe Plans": 14.725, "Tic Tac Toe": 1.9575, "Telegram": 2.2475, "Fawkes Night": 2.2475, "Peach Week": 2.2475, "Durov Day": 6.9750000000000005, "Heartbreak": 1.595, "Hodler": 5.075, "Burning Time": 1.9575, "Checklist": 2.2475, "Fund Manager": 2.2475, "Adult Tasks": 25.72, "Deadline": 2.2475, "Onyx Black": 1.775, "Black": 5.27, "just": 1.2325}, "Lunar Snake": {"Hot Cherry": 2.0250000000000004, "Psychedelic": 2.325, "Hellspawn": 2.0250000000000004, "Python Dev": 2.325, "Dragon Ball": 5.25, "Timelock": 2.325, "Synthwave": 4.199999999999999, "Soul Eater": 2.0250000000000004, "Onyx Black": 2.45, "Black": 5.73, "just": 1.275}, "Xmas Stocking": {"Onyx Black": 2.2199999999999998, "Black": 5.784999999999999, "just": 1.309}, "Snake Box": {"Onyx Black": 2.205, "Black": 5.465, "just": 1.394}, "Pet Snake": {"Onyx Black": 2.545, "Black": 5.695, "just": 1.6064999999999998}, "Candy Cane": {"Hex Pot": 3.14, "Grinch": 4.396, "Designer": 5.495, "Sticky Sweet": 2.1195000000000004, "Onyx Black": 2.285, "Black": 5.63, "just": 1.3345}, "Whip Cupcake": {"Toncoin": 2.5575, "Sponge Duck": 2.5575, "Bitcoin": 13.575000000000001, "Resistance": 5.7749999999999995, "Deep State": 2.2275, "Onyx Black": 2.2249999999999996, "Black": 5.525, "just": 1.4024999999999999}, "Big Year": {"Qing Dynasty": 2.9295, "Bitcoin": 5.292, "YouTubes": 2.9295, "Gold Mine": 6.614999999999999, "Balloons": 2.079, "The Hobbit": 3.78, "Creator": 2.9295, "Pokeball": 2.5515, "Pavel Durov": 12.445, "Telegram": 6.614999999999999, "The Nether": 2.9295, "Big Brother": 2.9295, "First Website": 2.2112999999999996, "Cheshire Cat": 2.9295, "Game Boy": 2.079, "Onyx Black": 3.9450000000000003, "Black": 9.945, "just": 1.6064999999999998}, "Homemade Cake": {"Onyx Black": 2.15, "Black": 5.664999999999999, "just": 1.615}, "Cookie Heart": {"Onyx Black": 2.5300000000000002, "Black": 6.535000000000001, "just": 1.581}, "Jester Hat": {"Onyx Black": 2.495, "Black": 5.8950000000000005, "just": 1.5215}, "Holiday Drink": {"Onyx Black": 2.69, "Black": 6.065, "just": 1.5979999999999999}, "Ginger Cookie": {"Onyx Black": 3.635, "Black": 6.734999999999999, "just": 1.6744999999999999}, "Hypno Lollipop": {"Onyx Black": 3.4350000000000005, "Black": 7.385, "just": 1.6744999999999999}, "Winter Wreath": {"Moon Cat": 90.99499999999999, "Onyx Black": 2.99, "Black": 6.74, "just": 1.6915}, "Party Sparkler": {"Onyx Black": 3.48, "Black": 7.425, "just": 1.666}, "Jingle Bells": {"Onyx Black": 3.03, "Black": 7.055, "just": 1.9209999999999998}, "Tama Gadget": {"Onyx Black": 3.46, "Black": 6.780000000000001, "just": 1.785}, "Jack-in-the-Box": {"Onyx Black": 3.125, "Black": 6.975, "just": 1.9124999999999999}, "Star Notepad": {"Onyx Black": 3.625, "Black": 10.649999999999999, "just": 1.9549999999999998}, "Easter Egg": {"Onyx Black": 3.8449999999999998, "Black": 10.925, "just": 2.499}, "Santa Hat": {"Onyx Black": 3.748, "Black": 9.248, "just": 2.363}, "Hex Pot": {"Onyx Black": 3.99, "Black": 9.83, "just": 2.3545}, "Restless Jar": {"Onyx Black": 3.565, "Black": 9.215, "just": 2.193}, "Lush Bouquet": {"Onyx Black": 5.25, "Black": 8.844999999999999, "just": 2.72}, "Spiced Wine": {"Onyx Black": 3.332, "Black": 7.135999999999999, "just": 2.176}, "Snow Globe": {"Onyx Black": 4.875, "Black": 11.13, "just": 2.3459999999999996}, "Joyful Bundle": {"Onyx Black": 4.9399999999999995, "Black": 9.66, "just": 2.448}, "Light Sword": {"Onyx Black": 4.456, "Black": 10.655999999999999, "just": 2.635}, "Witch Hat": {"Onyx Black": 4.5, "Black": 12.0, "just": 2.55}, "Bow Tie": {"Onyx Black": 4.918, "Black": 11.925999999999998, "just": 2.7285}, "Eternal Candle": {"Onyx Black": 5.354, "Black": 10.95, "just": 3.0515}, "Jelly Bunny": {"Onyx Black": 5.045, "Black": 10.185, "just": 2.8815}, "Bunny Muffin": {"Onyx Black": 5.3, "Black": 11.5, "just": 2.975}, "Spy Agaric": {"Onyx Black": 6.064, "Black": 10.463999999999999, "just": 2.924}, "Evil Eye": {"Onyx Black": 7.074, "Black": 13.474, "just": 3.2215}, "Snow Mittens": {"Onyx Black": 6.4, "Black": 8.4, "just": 3.4}, "Berry Box": {"Onyx Black": 5.236, "Black": 10.708, "just": 3.2809999999999997}, "Valentine Box": {"Onyx Black": 7.27, "Black": 14.281999999999998, "just": 4.1225}, "Sakura Flower": {"Onyx Black": 6.936, "Black": 16.14, "just": 4.165}, "Hanging Star": {"Onyx Black": 7.978, "Black": 15.382000000000001, "just": 5.0745}, "Sleigh Bell": {"Onyx Black": 11.7, "Black": 20.5, "just": 6.375}, "Love Candle": {"Onyx Black": 9.92, "Black": 14.8, "just": 6.8}, "Skull Flower": {"Onyx Black": 11.514, "Black": 18.474, "just": 6.961499999999999}, "Crystal Ball": {"Onyx Black": 12.51, "Black": 27.946, "just": 7.0125}, "Trapped Heart": {"Onyx Black": 12.174000000000001, "Black": 20.234, "just": 7.1315}, "Top Hat": {"Onyx Black": 15.056000000000001, "Black": 28.1, "just": 7.225}, "Love Potion": {"Onyx Black": 12.62, "Black": 23.816000000000003, "just": 8.245}, "Flying Broom": {"Onyx Black": 12.328000000000001, "Black": 17.288, "just": 8.058}, "Cupid Charm": {"Onyx Black": 17.122, "Black": 32.322, "just": 10.0895}, "Record Player": {"Onyx Black": 10.38, "Black": 20.619999999999997, "just": 6.545}, "Eternal Rose": {"Onyx Black": 18.759999999999998, "Black": 34.4, "just": 11.9}, "Mad Pumpkin": {"Onyx Black": 24.560000000000002, "Black": 39.16, "just": 16.66}, "Voodoo Doll": {"Onyx Black": 24.15, "Black": 46.254, "just": 14.526499999999999}, "Diamond Ring": {"Onyx Black": 21.304000000000002, "Black": 43.70399999999999, "just": 14.314}, "Toy Bear": {"Onyx Black": 30.75, "Black": 49.326, "just": 22.091499999999996}, "Vintage Cigar": {"Onyx Black": 36.53, "Black": 61.14999999999999, "just": 20.9015}, "Neko Helmet": {"Onyx Black": 37.0, "Black": 63.4, "just": 22.95}, "Low Rider": {"Onyx Black": 32.480000000000004, "Black": 80.08, "just": 21.08}, "Signet Ring": {"Onyx Black": 36.7, "Black": 71.896, "just": 22.525}, "Electric Skull": {"Onyx Black": 45.156000000000006, "Black": 75.56, "just": 27.71}, "Kissed Frog": {"Onyx Black": 45.0, "Black": 79.6, "just": 28.05}, "Swiss Watch": {"Onyx Black": 43.156, "Black": 71.956, "just": 29.970999999999997}, "Sharp Tongue": {"Onyx Black": 55.8, "Black": 140.6, "just": 34.85}, "Genie Lamp": {"Onyx Black": 67.88, "Black": 185.88, "just": 42.33}, "Scared Cat": {"Onyx Black": 73.4, "Black": 173.4, "just": 41.65}, "Westside Sign": {"Onyx Black": 63.8, "Black": 138.6, "just": 43.35}, "Bonded Ring": {"Onyx Black": 70.2, "Black": 174.2, "just": 48.449999999999996}, "Magic Potion": {"Onyx Black": 96.05, "Black": 171.25, "just": 63.5375}, "Gem Signet": {"Onyx Black": 121.6, "Black": 218.0, "just": 59.5}, "Moon Pendant": {"Onyx Black": 3.85, "Black": 10.055, "just": 1.8104999999999998}, "Stellar Rocket": {"Nostromo": 2.9700000000000006, "Gunship": 2.53, "Normandy": 3.4100000000000006, "Little Journey": 2.4200000000000004, "To The Moon": 21.999999999999996, "Mission Uranus": 68.60000000000001, "Chrome": 2.574, "Mega Death": 3.4100000000000006, "Space Veggie": 11.600000000000001, "Black Wing": 4.4, "Police Box": 2.9700000000000006, "Space Bot": 3.4100000000000006, "Doomsday": 2.75, "Telegram": 7.700000000000001, "Planet Express": 3.4100000000000006, "Bitcoin": 22.599999999999998, "Onyx Black": 4.75, "Black": 9.0, "just": 1.87}, "Jolly Chimp": {"Chimpool": 26.675000000000004, "Grayscale": 7.08, "Golden Monkey": 24.950000000000003, "Count Macaqula": 9.145000000000001, "Liberation": 20.650000000000002, "La Baboon": 50.31999999999999, "Chimp Imp": 7.08, "Jason": 7.965000000000001, "Cherub": 7.375, "Olympia": 9.145000000000001, "Smash King": 11.8, "Tired Primate": 39.8, "Bank Robber": 7.965000000000001, "Robo Kong": 6.490000000000001, "Gravity Bangs": 6.785, "Onyx Black": 7.945, "Black": 23.9, "just": 5.015000000000001}}