{"Snoop Dogg": {"Doggfather": 2.9155, "King Snoop": 5.0905000000000005, "Chrome": 2.2975, "Doberman": 3.3810000000000002, "Cold Topaz": 1.9115000000000002, "AI Dogg": 2.963, "Sapphire": 1.9210000000000003, "Green Light": 1.9210000000000003, "Black Diamond": 2.1965000000000003, "Goldizzle": 6.4955, "Onyx Black": 2.8099999999999996, "Black": 9.606923076923078, "just": 1.3855}, "Swag Bag": {"Snoop Life": 2.43, "Darkness": 1.9800000000000002, "Happy Herbs": 2.79, "Boiling Hot": 2.25, "April 20th": 2.79, "Take It Easy": 2.07, "Cashback": 2.79, "Missionary": 6.3, "Gin & Jewels": 2.3400000000000003, "Bulk Order": 2.07, "Onyx Black": 2.775, "Black": 6.895, "just": 1.53}, "Snoop Cigar": {"Onyx Black": 7.695, "Black": 17.145, "just": 3.7314999999999996}, "Lol Pop": {"Soap Bubbles": 1.344, "Andromeda": 1.536, "Watermelon": 1.4080000000000001, "Hexed Helix": 1.4080000000000001, "Comic Crunch": 1.344, "Blood Sucker": 1.472, "Sick Leave": 1.344, "Satellite": 1.7280000000000002, "Fire Vortex": 1.472, "Blood Ember": 1.6640000000000001, "Icicle": 1.4080000000000001, "Dark Sky": 1.472, "Nostalgia": 1.344, "Sailor Moon": 1.536, "Wonka Berry": 1.344, "Doodle Art": 1.536, "Cobweb": 1.344, "Einstein": 1.4080000000000001, "Cookie Dip": 1.4080000000000001, "Angelina": 1.9840000000000002, "Pumpkin": 1.472, "Mortal Sin": 3.5839999999999996, "Dark Portal": 1.6, "Romance": 1.344, "Milky Way": 1.4080000000000001, "Pink Foil": 1.344, "Jinxed": 1.472, "Shock Wave": 1.344, "Celestia": 1.9840000000000002, "Glowstick": 1.9840000000000002, "Sweetheart": 1.472, "Jolly Roger": 1.6640000000000001, "Love Bubbles": 1.6, "Rosebud": 1.6640000000000001, "Heart Pop": 1.4080000000000001, "Onyx Black": 1.8250000000000002, "Black": 5.135, "just": 1.088}, "B-Day Candle": {"Final Boss": 1.8599999999999999, "Payday": 2.4, "Kaboom!": 1.8599999999999999, "On Fire": 2.4, "Shocker": 1.8599999999999999, "Purr Magic": 2.4, "Happy Meows": 2.4, "Pixel Wish": 1.8599999999999999, "Onyx Black": 1.6, "Black": 4.6, "just": 1.02}, "Desk Calendar": {"Fund Manager": 1.8755, "Checklist": 1.8755, "Balloon Face": 1.573, "Durov Day": 2.42, "Adult Tasks": 4.234999999999999, "Telegram": 1.8755, "Deadline": 2.42, "Pepe Plans": 4.234999999999999, "Peach Week": 1.573, "Burning Time": 1.8755, "Sunday": 2.42, "Hodler": 4.234999999999999, "Independence": 3.388, "Fawkes Night": 3.388, "Heartbreak": 1.331, "Tic Tac Toe": 1.8755, "Investor": 4.234999999999999, "Onyx Black": 1.58, "Black": 4.855, "just": 1.0285}, "Lunar Snake": {"Hot Cherry": 2.0770000000000004, "Synthwave": 3.752, "Soul Eater": 2.0770000000000004, "Psychedelic": 2.0770000000000004, "Dragon Ball": 4.69, "Timelock": 1.675, "Python Dev": 2.0770000000000004, "Hellspawn": 2.0770000000000004, "Onyx Black": 2.02, "Black": 4.77, "just": 1.139}, "Xmas Stocking": {"Onyx Black": 1.895, "Black": 5.62, "just": 1.139}, "Snake Box": {"Onyx Black": 1.9, "Black": 4.7, "just": 1.105}, "Pet Snake": {"Onyx Black": 2.1950000000000003, "Black": 5.300000000000001, "just": 1.36}, "Candy Cane": {"Sticky Sweet": 2.1195000000000004, "Grinch": 2.4335, "Designer": 5.495, "Hex Pot": 3.14, "Onyx Black": 2.2800000000000002, "Black": 5.735, "just": 1.3345}, "Whip Cupcake": {"Resistance": 4.864999999999999, "Deep State": 2.1545, "Bitcoin": 4.864999999999999, "Sponge Duck": 2.78, "Toncoin": 2.1545, "Onyx Black": 2.0949999999999998, "Black": 5.180000000000001, "just": 1.1815}, "Big Year": {"Creator": 3.42, "Gold Mine": 4.787999999999999, "Cheshire Cat": 2.223, "YouTubes": 2.6505, "The Hobbit": 3.42, "Bitcoin": 4.787999999999999, "First Website": 2.1375, "Telegram": 4.787999999999999, "Qing Dynasty": 2.6505, "Big Brother": 2.6505, "Pokeball": 2.6505, "Pavel Durov": 4.787999999999999, "Game Boy": 2.223, "The Nether": 2.223, "Onyx Black": 2.725, "Black": 7.805000000000001, "just": 1.4535}, "Homemade Cake": {"Onyx Black": 1.895, "Black": 4.85, "just": 1.275}, "Cookie Heart": {"Onyx Black": 2.0949999999999998, "Black": 6.77, "just": 1.4364999999999999}, "Jester Hat": {"Onyx Black": 2.56, "Black": 6.065, "just": 1.3855}, "Holiday Drink": {"Onyx Black": 2.3, "Black": 5.66, "just": 1.462}, "Ginger Cookie": {"Onyx Black": 2.7800000000000002, "Black": 6.335000000000001, "just": 1.5045}, "Hypno Lollipop": {"Onyx Black": 2.68, "Black": 6.83, "just": 1.496}, "Winter Wreath": {"Onyx Black": 2.325, "Black": 7.975, "just": 1.4875}, "Party Sparkler": {"Onyx Black": 2.6950000000000003, "Black": 6.449999999999999, "just": 1.615}, "Jingle Bells": {"Onyx Black": 2.375, "Black": 5.324999999999999, "just": 1.4024999999999999}, "Tama Gadget": {"Onyx Black": 2.625, "Black": 6.135, "just": 1.5045}, "Jack-in-the-Box": {"Onyx Black": 2.685, "Black": 7.8950000000000005, "just": 1.734}, "Star Notepad": {"Onyx Black": 3.255, "Black": 9.129999999999999, "just": 1.751}, "Easter Egg": {"Onyx Black": 3.44, "Black": 10.684999999999999, "just": 2.0229999999999997}, "Santa Hat": {"Onyx Black": 3.37, "Black": 9.57, "just": 1.9889999999999999}, "Hex Pot": {"Onyx Black": 3.8, "Black": 7.924999999999999, "just": 2.04}, "Restless Jar": {"Onyx Black": 3.82, "Black": 7.67, "just": 1.9889999999999999}, "Lush Bouquet": {"Onyx Black": 3.39, "Black": 8.54, "just": 2.193}, "Spiced Wine": {"Onyx Black": 2.925, "Black": 7.9, "just": 1.6575}, "Snow Globe": {"Onyx Black": 3.995, "Black": 9.07, "just": 1.9889999999999999}, "Joyful Bundle": {"Onyx Black": 3.675, "Black": 8.475000000000001, "just": 2.1675}, "Light Sword": {"Onyx Black": 3.8850000000000002, "Black": 11.41, "just": 2.4395000000000002}, "Witch Hat": {"Onyx Black": 3.96, "Black": 10.11, "just": 2.3120000000000003}, "Bow Tie": {"Onyx Black": 4.725, "Black": 14.725, "just": 2.635}, "Eternal Candle": {"Onyx Black": 5.23, "Black": 10.23, "just": 2.516}, "Jelly Bunny": {"Onyx Black": 4.425, "Black": 10.12, "just": 2.7624999999999997}, "Bunny Muffin": {"Onyx Black": 4.51, "Black": 9.61, "just": 2.737}, "Spy Agaric": {"Onyx Black": 5.359999999999999, "Black": 11.215, "just": 2.4905}, "Evil Eye": {"Onyx Black": 5.745, "Black": 15.75, "just": 2.975}, "Snow Mittens": {"Onyx Black": 4.7, "Black": 8.735, "just": 2.5245}, "Berry Box": {"Onyx Black": 4.7250000000000005, "Black": 14.235000000000001, "just": 2.9495}, "Valentine Box": {"Onyx Black": 5.9, "Black": 10.915000000000001, "just": 3.2725}, "Sakura Flower": {"Onyx Black": 5.62, "Black": 17.975, "just": 3.3575}, "Hanging Star": {"Onyx Black": 7.620000000000001, "Black": 16.345, "just": 3.9865000000000004}, "Sleigh Bell": {"Onyx Black": 9.945, "Black": 17.939999999999998, "just": 5.0065}, "Love Candle": {"Onyx Black": 7.82, "Black": 15.42, "just": 5.388999999999999}, "Skull Flower": {"Onyx Black": 8.594999999999999, "Black": 19.450000000000003, "just": 5.015000000000001}, "Crystal Ball": {"Onyx Black": 10.185, "Black": 30.700000000000003, "just": 5.44}, "Trapped Heart": {"Onyx Black": 10.33, "Black": 23.73, "just": 6.511}, "Top Hat": {"Onyx Black": 16.105, "Black": 25.96, "just": 6.137}, "Love Potion": {"Onyx Black": 10.195, "Black": 26.544999999999998, "just": 6.8765}, "Flying Broom": {"Onyx Black": 10.120000000000001, "Black": 21.375, "just": 7.021}, "Cupid Charm": {"Onyx Black": 16.34, "Black": 34.84, "just": 8.228}, "Record Player": {"Onyx Black": 9.995000000000001, "Black": 23.994999999999997, "just": 6.7915}, "Eternal Rose": {"Onyx Black": 19.005, "Black": 33.005, "just": 11.058499999999999}, "Mad Pumpkin": {"Onyx Black": 18.18, "Black": 39.230000000000004, "just": 11.441}, "Voodoo Doll": {"Onyx Black": 20.455, "Black": 40.455, "just": 12.6735}, "Diamond Ring": {"Onyx Black": 20.245, "Black": 42.745, "just": 13.1665}, "Toy Bear": {"Onyx Black": 22.095, "Black": 51.38999999999999, "just": 15.1215}, "Vintage Cigar": {"Onyx Black": 43.44, "Black": 85.94, "just": 18.598}, "Neko Helmet": {"Onyx Black": 41.695, "Black": 71.695, "just": 19.8815}, "Low Rider": {"Onyx Black": 37.995000000000005, "Black": 106.5, "just": 19.55}, "Signet Ring": {"Onyx Black": 32.99, "Black": 90.49000000000001, "just": 19.533}, "Electric Skull": {"Onyx Black": 37.5, "Black": 70.0, "just": 22.099999999999998}, "Kissed Frog": {"Onyx Black": 45.5, "Black": 78.995, "just": 28.05}, "Swiss Watch": {"Onyx Black": 51.0, "Black": 93.5, "just": 27.2}, "Sharp Tongue": {"Onyx Black": 45.655, "Black": 80.655, "just": 26.6135}, "Genie Lamp": {"Onyx Black": 59.864999999999995, "Black": 319.865, "just": 33.7705}, "Scared Cat": {"Onyx Black": 66.0, "Black": 163.0, "just": 35.699999999999996}, "Westside Sign": {"Onyx Black": 70.94, "Black": 149.44, "just": 41.548}, "Bonded Ring": {"Onyx Black": 72.09, "Black": 199.59, "just": 41.803}, "Magic Potion": {"Onyx Black": 88.5, "Black": 184.995, "just": 50.15}, "Gem Signet": {"Onyx Black": 88.495, "Black": 361.495, "just": 48.4415}, "Moon Pendant": {"Onyx Black": 3.445, "Black": 9.375, "just": 1.4875}, "Stellar Rocket": {"Telegram": 6.3, "Bitcoin": 6.3, "Mission Uranus": 6.3, "To The Moon": 6.3, "Space Veggie": 6.3, "Onyx Black": 2.9000000000000004, "Black": 8.75, "just": 1.53}, "Jolly Chimp": {"Chimpool": 14.0, "La Baboon": 14.0, "Tired Primate": 14.0, "Golden Monkey": 14.0, "Liberation": 14.0, "Onyx Black": 6.095, "Black": 18.95, "just": 3.4}}